rknn_toolkit2-2.3.2.dist-info/top_level.txt
rknn_toolkit2-2.3.2.dist-info/METADATA
rknn_toolkit2-2.3.2.dist-info/WHEEL
rknn_toolkit2-2.3.2.dist-info/RECORD
rknn/VERSION
rknn/api/ir_graph.cpython-38-x86_64-linux-gnu.so
rknn/api/quantizer.cpython-38-x86_64-linux-gnu.so
rknn/api/bias_correction.cpython-38-x86_64-linux-gnu.so
rknn/api/base_utils.cpython-38-x86_64-linux-gnu.so
rknn/api/simulator.cpython-38-x86_64-linux-gnu.so
rknn/api/rknn_base.cpython-38-x86_64-linux-gnu.so
rknn/api/graph_optimizer.cpython-38-x86_64-linux-gnu.so
rknn/api/quant_optimizer.cpython-38-x86_64-linux-gnu.so
rknn/api/quant_utils.cpython-38-x86_64-linux-gnu.so
rknn/api/sparse_weight.cpython-38-x86_64-linux-gnu.so
rknn/api/load_checker.cpython-38-x86_64-linux-gnu.so
rknn/api/rknn_runtime.cpython-38-x86_64-linux-gnu.so
rknn/api/fuse_rules.cpython-38-x86_64-linux-gnu.so
rknn/api/convert.py
rknn/api/rknn_platform.cpython-38-x86_64-linux-gnu.so
rknn/api/rknn_utils.cpython-38-x86_64-linux-gnu.so
rknn/api/ir_utils.cpython-38-x86_64-linux-gnu.so
rknn/api/mmse_quant2.cpython-38-x86_64-linux-gnu.so
rknn/api/act_equalization.cpython-38-x86_64-linux-gnu.so
rknn/api/auto_hybrid.cpython-38-x86_64-linux-gnu.so
rknn/api/stream_op.cpython-38-x86_64-linux-gnu.so
rknn/api/hybrid_proposal.cpython-38-x86_64-linux-gnu.so
rknn/api/rknn_convert.py
rknn/api/weight_equalization.cpython-38-x86_64-linux-gnu.so
rknn/api/codegen.cpython-38-x86_64-linux-gnu.so
rknn/api/custom_op.cpython-38-x86_64-linux-gnu.so
rknn/api/__init__.py
rknn/api/rknn_compiler.cpython-38-x86_64-linux-gnu.so
rknn/api/model_pruning.cpython-38-x86_64-linux-gnu.so
rknn/api/session.cpython-38-x86_64-linux-gnu.so
rknn/api/gdq_quant.cpython-38-x86_64-linux-gnu.so
rknn/api/rknn.py
rknn/api/libcpputils2.cpython-38-x86_64-linux-gnu.so
rknn/api/rknn_log.cpython-38-x86_64-linux-gnu.so
rknn/api/lib/linux-x86_64/libcpputils2.so
rknn/api/lib/linux-x86_64/librknnc.so
rknn/api/lib/linux-x86_64/librknn_api.so
rknn/api/rules/swap.cpython-38-x86_64-linux-gnu.so
rknn/api/rules/active.cpython-38-x86_64-linux-gnu.so
rknn/api/rules/elemwise.cpython-38-x86_64-linux-gnu.so
