Metadata-Version: 2.1
Name: rknn-toolkit2
Version: 2.3.2
Summary: Rockchip Neural Network Toolkit2. (commit: bd980be9)
Home-page: https://github.com/airockchip/rknn-toolkit2
Author: ai@rock-chips.com
Author-email: ai@rock-chips.com
Classifier: Programming Language :: Python :: 3
Classifier: Operating System :: POSIX :: Linux
Requires-Dist: protobuf <=4.25.4,>=4.21.6
Requires-Dist: psutil >=5.9.0
Requires-Dist: ruamel.yaml >=0.17.4
Requires-Dist: scipy >=1.5.4
Requires-Dist: tqdm >=4.64.0
Requires-Dist: opencv-python >=4.5.5.64
Requires-Dist: fast-histogram >=0.11
Requires-Dist: numpy <=1.26.4
Requires-Dist: onnx >=1.16.1
Requires-Dist: onnxruntime >=1.10.0
Requires-Dist: torch <=2.4.0,>=1.10.1
